{"elapsed":"6.572","endpoint-url":"https://map.cornwall.gov.uk/arcgis/services/inspire/inspire_landbuildings/MapServer/WFSServer?request=GetFeature&service=WFS&typename=inspire_inspire_landbuildings:cornwall_council_brownfield_register","entry-date":"2021-10-10T00:16:12.256150","request-headers":{"Accept":"*/*","Accept-Encoding":"gzip, deflate","Connection":"keep-alive","User-Agent":"Digital Land"},"resource":"66418d56ad4d0f4b8f7c952909fa5d51ffde4c7081ddfc7a9c458e30a83e3c6f","response-headers":{"Cache-Control":"no-cache","Content-Length":"709091","Content-Type":"application/xml;charset=UTF-8","Date":"Sun, 10 Oct 2021 00:16:20 GMT","Expires":"-1","Pragma":"no-cache","Server":"Microsoft-IIS/8.5, ","Set-Cookie":"BNI_persistence=-oMuwJWTY8xe9gAXchZ7LZIV_9pUzvcH6n02Rh9PDFOEvsUwJbyE5qW3fa8v68LXEfaTfd8MYXGJnUEc4OwbWw==; Path=/","X-AspNet-Version":"4.0.30319","X-Content-Type-Options":"nosniff","X-Powered-By":"ASP.NET","X-UA-Compatible":"IE=Edge","X-XSS-Protection":"1; mode=block","accept":"text/html, image/gif, image/jpeg, *; q=.2, */*; q=.2","host":"vmg-app-cen-d32.cc.cornwallonline.net:6443","referer":"80a6b48e-c37a-4d16-a919-d6b01aad057a","referrer":"80a6b48e-c37a-4d16-a919-d6b01aad057a","response_buffer_size":"8192","response_character_encoding":"UTF-8","response_content_type":"application/xml","user-agent":"Java/11.0.6"},"ssl-verify":true,"status":"200"}